{
  "hash": "a7835681",
  "configHash": "06ec0f56",
  "lockfileHash": "fba1b56a",
  "browserHash": "6d01ed99",
  "optimized": {
    "vue": {
      "src": "../../../../node_modules/vue/dist/vue.runtime.esm-bundler.js",
      "file": "vue.js",
      "fileHash": "5c13343f",
      "needsInterop": false
    },
    "vitepress > @vue/devtools-api": {
      "src": "../../../../node_modules/@vue/devtools-api/dist/index.js",
      "file": "vitepress___@vue_devtools-api.js",
      "fileHash": "942987b4",
      "needsInterop": false
    },
    "vitepress > @vueuse/core": {
      "src": "../../../../node_modules/@vueuse/core/index.mjs",
      "file": "vitepress___@vueuse_core.js",
      "fileHash": "14773445",
      "needsInterop": false
    },
    "@theme/index": {
      "src": "../../../../node_modules/vitepress/dist/client/theme-default/index.js",
      "file": "@theme_index.js",
      "fileHash": "4734d1b8",
      "needsInterop": false
    }
  },
  "chunks": {
    "chunk-4FWP2Y5K": {
      "file": "chunk-4FWP2Y5K.js"
    },
    "chunk-PAUCAATC": {
      "file": "chunk-PAUCAATC.js"
    }
  }
}