{"contact.md":"jxOxib1N","multi-submission.md":"vmN52i_l","simple-search.md":"DuGTVQAZ","api-examples.md":"BSU5M6ou","sdf-download.md":"D42nnF_W","single-submission.md":"DmKXQDzB","about.md":"CkCRBmJt","index.md":"Bgsc7VCQ","advanced-search.md":"CyBoTh0w","download-api.md":"UCF3q0eR","markdown-examples.md":"DGZDW-VT","similarity-search.md":"BiUJWNkA","license.md":"DDpJzdRp","report-submission.md":"B9Jvt970","schemas-api.md":"jmZp8tkf","download.md":"BQ5Ph9j4","substructure-search.md":"BG6d9jjX","installation.md":"DKwridaw","auth-api.md":"-OQT4ZF1","structure-search.md":"CcT_3tmD","browse.md":"BIXY2ZJa","submission-api.md":"BnWez3I0","collection-submission.md":"DEd1vv6-","draw-structure.md":"CDXAxkRa","search-api.md":"BLPy9tHF","analysis.md":"CyZup_wk","faqs.md":"Cvs3yL4F","issues.md":"D8iWAUtH","sources.md":"DKxjGHN-","api-submission.md":"C-4xVe_K","introduction.md":"GpC-T3IZ","db-schema.md":"B4uljbCw"}
